pagege/__init__.py
pagege/example.py
mipol-0.0.1.dist-info/LICENSE
mipol-0.0.1.dist-info/METADATA
mipol-0.0.1.dist-info/WHEEL
mipol-0.0.1.dist-info/top_level.txt
mipol-0.0.1.dist-info/RECORD
