Metadata-Version: 2.1
Name: mipol
Version: 0.0.1
Summary: Advance Toolset
Author-email: JustOnPy <justiceisvic@gmail.com>
Classifier: Programming Language :: Python :: 3
Classifier: License :: OSI Approved :: MIT License
Classifier: Operating System :: OS Independent
Requires-Python: >=3.7
License-File: LICENSE
